setup.py
JMI_FeatureSelection_primitive/JMIFeatSelector.py
JMI_FeatureSelection_primitive/JMI_FeatureSelection_primitive.ctf
JMI_FeatureSelection_primitive/__init__.py
JMI_FeatureSelection_primitive/base.py
JMI_FeatureSelection_primitive/supervised_learning.py
JMI_FeatureSelection_primitive.egg-info/PKG-INFO
JMI_FeatureSelection_primitive.egg-info/SOURCES.txt
JMI_FeatureSelection_primitive.egg-info/dependency_links.txt
JMI_FeatureSelection_primitive.egg-info/top_level.txt