Metadata-Version: 1.0
Name: JMI-FeatureSelection-primitive
Version: 2.0.1
Summary: JSTMB feature selection combined with joint mutual information code
Home-page: https://www.ecse.rpi.edu/~cvrl/liuk
Author: Keyi Liu
Author-email: liuk7@rpi.edu
License: UNKNOWN
Platform: Linux
Platform: Windows
Platform: MacOS
